ramalama/__init__.py
ramalama/amdkfd.py
ramalama/annotations.py
ramalama/arg_types.py
ramalama/chat.py
ramalama/cli.py
ramalama/cli_arg_normalization.py
ramalama/common.py
ramalama/compat.py
ramalama/compose.py
ramalama/config.py
ramalama/console.py
ramalama/endian.py
ramalama/engine.py
ramalama/file.py
ramalama/hf_style_repo_base.py
ramalama/http_client.py
ramalama/kube.py
ramalama/layered_config.py
ramalama/log_levels.py
ramalama/logger.py
ramalama/oci_tools.py
ramalama/ollama_repo_utils.py
ramalama/path_utils.py
ramalama/proxy_support.py
ramalama/py.typed
ramalama/quadlet.py
ramalama/rag.py
ramalama/shortnames.py
ramalama/stack.py
ramalama/toml_parser.py
ramalama/version.py
ramalama/command/context.py
ramalama/command/error.py
ramalama/command/factory.py
ramalama/command/schema.py
ramalama/daemon/daemon.py
ramalama/daemon/logging.py
ramalama/daemon/dto/errors.py
ramalama/daemon/dto/model.py
ramalama/daemon/dto/serve.py
ramalama/daemon/handler/base.py
ramalama/daemon/handler/daemon.py
ramalama/daemon/handler/proxy.py
ramalama/daemon/handler/ramalama.py
ramalama/daemon/service/model_runner.py
ramalama/file_loaders/__init__.py
ramalama/file_loaders/file_manager.py
ramalama/file_loaders/file_types/__init__.py
ramalama/file_loaders/file_types/base.py
ramalama/file_loaders/file_types/image.py
ramalama/file_loaders/file_types/pdf.py
ramalama/file_loaders/file_types/txt.py
ramalama/mcp/mcp_agent.py
ramalama/mcp/mcp_client.py
ramalama/model_inspect/__init__.py
ramalama/model_inspect/base_info.py
ramalama/model_inspect/error.py
ramalama/model_inspect/gguf_info.py
ramalama/model_inspect/gguf_parser.py
ramalama/model_inspect/safetensor_info.py
ramalama/model_inspect/safetensor_parser.py
ramalama/model_store/constants.py
ramalama/model_store/global_store.py
ramalama/model_store/go2jinja.py
ramalama/model_store/reffile.py
ramalama/model_store/snapshot_file.py
ramalama/model_store/store.py
ramalama/model_store/template_conversion.py
ramalama/transports/__init__.py
ramalama-0.16.0.dist-info/licenses/LICENSE
ramalama-0.16.0.dist-info/METADATA
ramalama-0.16.0.dist-info/WHEEL
ramalama-0.16.0.dist-info/entry_points.txt
ramalama-0.16.0.dist-info/top_level.txt
ramalama-0.16.0.dist-info/RECORD
