Metadata-Version: 2.4
Name: ramalama
Version: 0.16.0
Summary: RamaLama is a command line tool for working with AI LLM models.
Maintainer-email: Dan Walsh <dwalsh@redhat.com>, Eric Curtin <ecurtin@redhat.com>
License: MIT
Project-URL: Homepage, https://github.com/containers/ramalama
Project-URL: Repository, https://github.com/containers/ramalama
Project-URL: Issues, https://github.com/containers/ramalama/issues
Project-URL: Discussions, https://github.com/containers/ramalama/discussions
Project-URL: Discord, https://discord.gg/MkCXuTRBUn
Project-URL: Matrix, https://matrix.to/#/#ramalama:fedoraproject.org
Keywords: ramalama,llama,ai,llm,large-language-model,inference,containers,podman,docker,gpu,rag
Classifier: License :: OSI Approved :: MIT License
Classifier: Environment :: Console
Classifier: Intended Audience :: Developers
Classifier: Intended Audience :: Science/Research
Classifier: Intended Audience :: System Administrators
Classifier: Operating System :: MacOS :: MacOS X
Classifier: Operating System :: Microsoft :: Windows
Classifier: Operating System :: POSIX :: Linux
Classifier: Programming Language :: Python
Classifier: Programming Language :: Python :: 3
Classifier: Programming Language :: Python :: 3.10
Classifier: Programming Language :: Python :: 3.11
Classifier: Programming Language :: Python :: 3.12
Classifier: Programming Language :: Python :: 3.13
Classifier: Programming Language :: Python :: 3.14
Classifier: Topic :: Scientific/Engineering :: Artificial Intelligence
Classifier: Topic :: Utilities
Requires-Python: >=3.10
License-File: LICENSE
Requires-Dist: argcomplete
Requires-Dist: pyyaml
Requires-Dist: jsonschema
Requires-Dist: jinja2
Provides-Extra: dev
Requires-Dist: argcomplete~=3.0; extra == "dev"
Requires-Dist: bcrypt; extra == "dev"
Requires-Dist: black~=25.0; extra == "dev"
Requires-Dist: codespell~=2.0; extra == "dev"
Requires-Dist: flake8~=7.0; extra == "dev"
Requires-Dist: huggingface_hub~=1.2.1; extra == "dev"
Requires-Dist: hypothesis>=6.135.26; extra == "dev"
Requires-Dist: isort~=7.0; extra == "dev"
Requires-Dist: pytest~=9.0; extra == "dev"
Requires-Dist: wheel~=0.45.0; extra == "dev"
Requires-Dist: mypy; extra == "dev"
Requires-Dist: types-PyYAML; extra == "dev"
Requires-Dist: types-jsonschema; extra == "dev"
Requires-Dist: tox; extra == "dev"
Provides-Extra: cov
Requires-Dist: ramalama[dev]; extra == "cov"
Requires-Dist: pytest-cov; extra == "cov"
Provides-Extra: cov-detailed
Requires-Dist: ramalama[cov]; extra == "cov-detailed"
Requires-Dist: pytest-func-cov; extra == "cov-detailed"
Requires-Dist: pytest-report; extra == "cov-detailed"
Requires-Dist: pytest-json; extra == "cov-detailed"
Requires-Dist: pytest-html; extra == "cov-detailed"
Dynamic: license-file
